[
  {
    "ContainingType": "LMS_SoulCode.Features.Auth.Controllers.AuthController",
    "Method": "ForgotPassword",
    "RelativePath": "api/Auth/forgot-password",
    "HttpMethod": "POST",
    "IsController": true,
    "Order": 0,
    "Parameters": [
      {
        "Name": "request",
        "Type": "LMS_SoulCode.Features.Auth.Models.ForgotPasswordRequest",
        "IsRequired": true
      }
    ],
    "ReturnTypes": []
  },
  {
    "ContainingType": "LMS_SoulCode.Features.Auth.Controllers.AuthController",
    "Method": "Login",
    "RelativePath": "api/Auth/login",
    "HttpMethod": "POST",
    "IsController": true,
    "Order": 0,
    "Parameters": [
      {
        "Name": "request",
        "Type": "LMS_SoulCode.Features.Auth.Models.LoginRequest",
        "IsRequired": true
      }
    ],
    "ReturnTypes": []
  },
  {
    "ContainingType": "LMS_SoulCode.Features.Auth.Controllers.AuthController",
    "Method": "Register",
    "RelativePath": "api/Auth/register",
    "HttpMethod": "POST",
    "IsController": true,
    "Order": 0,
    "Parameters": [
      {
        "Name": "request",
        "Type": "LMS_SoulCode.Features.Auth.Models.RegisterRequest",
        "IsRequired": true
      }
    ],
    "ReturnTypes": []
  },
  {
    "ContainingType": "LMS_SoulCode.Features.Auth.Controllers.AuthController",
    "Method": "ResetPassword",
    "RelativePath": "api/Auth/reset-password",
    "HttpMethod": "POST",
    "IsController": true,
    "Order": 0,
    "Parameters": [
      {
        "Name": "request",
        "Type": "LMS_SoulCode.Features.Auth.Models.ResetPasswordRequest",
        "IsRequired": true
      }
    ],
    "ReturnTypes": []
  },
  {
    "ContainingType": "LMS_SoulCode.Features.UserPermissions.Controllers.PermissionController",
    "Method": "GetById",
    "RelativePath": "api/Permission/{id}",
    "HttpMethod": "GET",
    "IsController": true,
    "Order": 0,
    "Parameters": [
      {
        "Name": "id",
        "Type": "System.Int32",
        "IsRequired": true
      }
    ],
    "ReturnTypes": []
  },
  {
    "ContainingType": "LMS_SoulCode.Features.UserPermissions.Controllers.PermissionController",
    "Method": "Create",
    "RelativePath": "api/Permission/create",
    "HttpMethod": "POST",
    "IsController": true,
    "Order": 0,
    "Parameters": [
      {
        "Name": "request",
        "Type": "LMS_SoulCode.Features.UserPermissions.Controllers.CreatePermissionRequest",
        "IsRequired": true
      }
    ],
    "ReturnTypes": []
  },
  {
    "ContainingType": "LMS_SoulCode.Features.UserPermissions.Controllers.PermissionController",
    "Method": "Delete",
    "RelativePath": "api/Permission/delete/{id}",
    "HttpMethod": "DELETE",
    "IsController": true,
    "Order": 0,
    "Parameters": [
      {
        "Name": "id",
        "Type": "System.Int32",
        "IsRequired": true
      }
    ],
    "ReturnTypes": []
  },
  {
    "ContainingType": "LMS_SoulCode.Features.UserPermissions.Controllers.PermissionController",
    "Method": "GetAll",
    "RelativePath": "api/Permission/list",
    "HttpMethod": "GET",
    "IsController": true,
    "Order": 0,
    "Parameters": [],
    "ReturnTypes": []
  },
  {
    "ContainingType": "LMS_SoulCode.Features.UserPermissions.Controllers.PermissionController",
    "Method": "Update",
    "RelativePath": "api/Permission/update/{id}",
    "HttpMethod": "PUT",
    "IsController": true,
    "Order": 0,
    "Parameters": [
      {
        "Name": "id",
        "Type": "System.Int32",
        "IsRequired": true
      },
      {
        "Name": "request",
        "Type": "LMS_SoulCode.Features.UserPermissions.Controllers.UpdatePermissionRequest",
        "IsRequired": true
      }
    ],
    "ReturnTypes": []
  },
  {
    "ContainingType": "LMS_SoulCode.Features.UserPermissions.Controllers.RoleController",
    "Method": "GetById",
    "RelativePath": "api/Role/{id}",
    "HttpMethod": "GET",
    "IsController": true,
    "Order": 0,
    "Parameters": [
      {
        "Name": "id",
        "Type": "System.Int32",
        "IsRequired": true
      }
    ],
    "ReturnTypes": []
  },
  {
    "ContainingType": "LMS_SoulCode.Features.UserPermissions.Controllers.RoleController",
    "Method": "Create",
    "RelativePath": "api/Role/create",
    "HttpMethod": "POST",
    "IsController": true,
    "Order": 0,
    "Parameters": [
      {
        "Name": "request",
        "Type": "LMS_SoulCode.Features.UserPermissions.Controllers.CreateRoleRequest",
        "IsRequired": true
      }
    ],
    "ReturnTypes": []
  },
  {
    "ContainingType": "LMS_SoulCode.Features.UserPermissions.Controllers.RoleController",
    "Method": "Delete",
    "RelativePath": "api/Role/delete/{id}",
    "HttpMethod": "DELETE",
    "IsController": true,
    "Order": 0,
    "Parameters": [
      {
        "Name": "id",
        "Type": "System.Int32",
        "IsRequired": true
      }
    ],
    "ReturnTypes": []
  },
  {
    "ContainingType": "LMS_SoulCode.Features.UserPermissions.Controllers.RoleController",
    "Method": "GetAll",
    "RelativePath": "api/Role/list",
    "HttpMethod": "GET",
    "IsController": true,
    "Order": 0,
    "Parameters": [],
    "ReturnTypes": []
  },
  {
    "ContainingType": "LMS_SoulCode.Features.UserPermissions.Controllers.RoleController",
    "Method": "Update",
    "RelativePath": "api/Role/update/{id}",
    "HttpMethod": "PUT",
    "IsController": true,
    "Order": 0,
    "Parameters": [
      {
        "Name": "id",
        "Type": "System.Int32",
        "IsRequired": true
      },
      {
        "Name": "request",
        "Type": "LMS_SoulCode.Features.UserPermissions.Controllers.UpdateRoleRequest",
        "IsRequired": true
      }
    ],
    "ReturnTypes": []
  },
  {
    "ContainingType": "LMS_SoulCode.Features.UserPermissions.Controllers.UserRoleController",
    "Method": "GetRoles",
    "RelativePath": "api/UserRole/{userId}",
    "HttpMethod": "GET",
    "IsController": true,
    "Order": 0,
    "Parameters": [
      {
        "Name": "userId",
        "Type": "System.Int32",
        "IsRequired": true
      }
    ],
    "ReturnTypes": []
  },
  {
    "ContainingType": "LMS_SoulCode.Features.UserPermissions.Controllers.UserRoleController",
    "Method": "AssignRole",
    "RelativePath": "api/UserRole/assign",
    "HttpMethod": "POST",
    "IsController": true,
    "Order": 0,
    "Parameters": [
      {
        "Name": "userId",
        "Type": "System.Int32",
        "IsRequired": false
      },
      {
        "Name": "roleId",
        "Type": "System.Int32",
        "IsRequired": false
      }
    ],
    "ReturnTypes": []
  },
  {
    "ContainingType": "LMS_SoulCode.Features.UserPermissions.Controllers.UserRoleController",
    "Method": "RemoveRole",
    "RelativePath": "api/UserRole/remove",
    "HttpMethod": "DELETE",
    "IsController": true,
    "Order": 0,
    "Parameters": [
      {
        "Name": "userId",
        "Type": "System.Int32",
        "IsRequired": false
      },
      {
        "Name": "roleId",
        "Type": "System.Int32",
        "IsRequired": false
      }
    ],
    "ReturnTypes": []
  }
]